{"descriptions": {"5fb84cbd-30a0-4c24-b011-21e419ac8af9": {"action_sequence": [{"action": {"tool": "copyFromInput"}, "grid": [[0, 0, 0, 0, 0], [0, 0, 0, 0, 0], [0, 0, 1, 0, 1], [0, 0, 5, 0, 5], [5, 5, 5, 5, 5]], "time": 17.472}, {"action": {"symbol": "0", "tool": "edit", "x": "2", "y": "2"}, "grid": [[0, 0, 0, 0, 0], [0, 0, 0, 0, 0], [0, 0, 0, 0, 1], [0, 0, 5, 0, 5], [5, 5, 5, 5, 5]], "time": 25.228}, {"action": {"symbol": "0", "tool": "edit", "x": "2", "y": "4"}, "grid": [[0, 0, 0, 0, 0], [0, 0, 0, 0, 0], [0, 0, 0, 0, 0], [0, 0, 5, 0, 5], [5, 5, 5, 5, 5]], "time": 26.258}, {"action": {"symbol": "1", "tool": "edit", "x": "4", "y": "2"}, "grid": [[0, 0, 0, 0, 0], [0, 0, 0, 0, 0], [0, 0, 0, 0, 0], [0, 0, 5, 0, 5], [5, 5, 1, 5, 5]], "time": 29.566}, {"action": {"symbol": "1", "tool": "edit", "x": "4", "y": "4"}, "grid": [[0, 0, 0, 0, 0], [0, 0, 0, 0, 0], [0, 0, 0, 0, 0], [0, 0, 5, 0, 5], [5, 5, 1, 5, 1]], "time": 30.117}, {"action": {"correct": true, "tool": "check"}, "grid": [[0, 0, 0, 0, 0], [0, 0, 0, 0, 0], [0, 0, 0, 0, 0], [0, 0, 5, 0, 5], [5, 5, 1, 5, 1]], "time": 31.989}], "attempt_jsons": [[[0, 0, 0, 0, 0], [0, 0, 0, 0, 0], [0, 0, 0, 0, 0], [0, 0, 5, 0, 5], [5, 5, 1, 5, 1]]], "builds": {"QlZ8TQnrYQ5QSoEhTQLJ": {"action_sequence": [{"action": {"tool": "copyFromInput"}, "grid": [[0, 0, 0, 0, 0], [0, 0, 0, 0, 0], [0, 0, 1, 0, 1], [0, 0, 5, 0, 5], [5, 5, 5, 5, 5]], "time": 23.93}, {"action": {"correct": false, "tool": "check"}, "grid": [[0, 0, 0, 0, 0], [0, 0, 0, 0, 0], [0, 0, 1, 0, 1], [0, 0, 5, 0, 5], [5, 5, 5, 5, 5]], "time": 31.35}, {"action": {"symbol": "1", "tool": "edit", "x": "3", "y": "0"}, "grid": [[0, 0, 0, 0, 0], [0, 0, 0, 0, 0], [0, 0, 1, 0, 1], [1, 0, 5, 0, 5], [5, 5, 5, 5, 5]], "time": 41.445}, {"action": {"symbol": "1", "tool": "edit", "x": "3", "y": "1"}, "grid": [[0, 0, 0, 0, 0], [0, 0, 0, 0, 0], [0, 0, 1, 0, 1], [1, 1, 5, 0, 5], [5, 5, 5, 5, 5]], "time": 41.869}, {"action": {"symbol": "1", "tool": "edit", "x": "2", "y": "1"}, "grid": [[0, 0, 0, 0, 0], [0, 0, 0, 0, 0], [0, 1, 1, 0, 1], [1, 1, 5, 0, 5], [5, 5, 5, 5, 5]], "time": 42.193}, {"action": {"symbol": "1", "tool": "edit", "x": "2", "y": "0"}, "grid": [[0, 0, 0, 0, 0], [0, 0, 0, 0, 0], [1, 1, 1, 0, 1], [1, 1, 5, 0, 5], [5, 5, 5, 5, 5]], "time": 42.539}, {"action": {"symbol": "1", "tool": "edit", "x": "1", "y": "0"}, "grid": [[0, 0, 0, 0, 0], [1, 0, 0, 0, 0], [1, 1, 1, 0, 1], [1, 1, 5, 0, 5], [5, 5, 5, 5, 5]], "time": 42.853}, {"action": {"symbol": "1", "tool": "edit", "x": "1", "y": "1"}, "grid": [[0, 0, 0, 0, 0], [1, 1, 0, 0, 0], [1, 1, 1, 0, 1], [1, 1, 5, 0, 5], [5, 5, 5, 5, 5]], "time": 43.193}, {"action": {"symbol": "1", "tool": "edit", "x": "0", "y": "1"}, "grid": [[0, 1, 0, 0, 0], [1, 1, 0, 0, 0], [1, 1, 1, 0, 1], [1, 1, 5, 0, 5], [5, 5, 5, 5, 5]], "time": 43.523}, {"action": {"symbol": "1", "tool": "edit", "x": "0", "y": "0"}, "grid": [[1, 1, 0, 0, 0], [1, 1, 0, 0, 0], [1, 1, 1, 0, 1], [1, 1, 5, 0, 5], [5, 5, 5, 5, 5]], "time": 43.855}, {"action": {"symbol": "1", "tool": "edit", "x": "0", "y": "2"}, "grid": [[1, 1, 1, 0, 0], [1, 1, 0, 0, 0], [1, 1, 1, 0, 1], [1, 1, 5, 0, 5], [5, 5, 5, 5, 5]], "time": 44.271}, {"action": {"symbol": "1", "tool": "edit", "x": "0", "y": "3"}, "grid": [[1, 1, 1, 1, 0], [1, 1, 0, 0, 0], [1, 1, 1, 0, 1], [1, 1, 5, 0, 5], [5, 5, 5, 5, 5]], "time": 44.611}, {"action": {"symbol": "1", "tool": "edit", "x": "0", "y": "4"}, "grid": [[1, 1, 1, 1, 1], [1, 1, 0, 0, 0], [1, 1, 1, 0, 1], [1, 1, 5, 0, 5], [5, 5, 5, 5, 5]], "time": 44.949}, {"action": {"symbol": "1", "tool": "edit", "x": "1", "y": "4"}, "grid": [[1, 1, 1, 1, 1], [1, 1, 0, 0, 1], [1, 1, 1, 0, 1], [1, 1, 5, 0, 5], [5, 5, 5, 5, 5]], "time": 45.294}, {"action": {"symbol": "1", "tool": "edit", "x": "1", "y": "3"}, "grid": [[1, 1, 1, 1, 1], [1, 1, 0, 1, 1], [1, 1, 1, 0, 1], [1, 1, 5, 0, 5], [5, 5, 5, 5, 5]], "time": 45.657}, {"action": {"symbol": "1", "tool": "edit", "x": "1", "y": "2"}, "grid": [[1, 1, 1, 1, 1], [1, 1, 1, 1, 1], [1, 1, 1, 0, 1], [1, 1, 5, 0, 5], [5, 5, 5, 5, 5]], "time": 45.981}, {"action": {"symbol": "1", "tool": "edit", "x": "2", "y": "3"}, "grid": [[1, 1, 1, 1, 1], [1, 1, 1, 1, 1], [1, 1, 1, 1, 1], [1, 1, 5, 0, 5], [5, 5, 5, 5, 5]], "time": 46.367}, {"action": {"symbol": "1", "tool": "edit", "x": "3", "y": "3"}, "grid": [[1, 1, 1, 1, 1], [1, 1, 1, 1, 1], [1, 1, 1, 1, 1], [1, 1, 5, 1, 5], [5, 5, 5, 5, 5]], "time": 46.823}, {"action": {"correct": false, "tool": "check"}, "grid": [[1, 1, 1, 1, 1], [1, 1, 1, 1, 1], [1, 1, 1, 1, 1], [1, 1, 5, 1, 5], [5, 5, 5, 5, 5]], "time": 47.815}, {"action": {"symbol": "0", "tool": "edit", "x": "2", "y": "2"}, "grid": [[1, 1, 1, 1, 1], [1, 1, 1, 1, 1], [1, 1, 0, 1, 1], [1, 1, 5, 1, 5], [5, 5, 5, 5, 5]], "time": 50.226}, {"action": {"symbol": "0", "tool": "edit", "x": "2", "y": "4"}, "grid": [[1, 1, 1, 1, 1], [1, 1, 1, 1, 1], [1, 1, 0, 1, 0], [1, 1, 5, 1, 5], [5, 5, 5, 5, 5]], "time": 50.739}, {"action": {"correct": false, "tool": "check"}, "grid": [[1, 1, 1, 1, 1], [1, 1, 1, 1, 1], [1, 1, 0, 1, 0], [1, 1, 5, 1, 5], [5, 5, 5, 5, 5]], "time": 51.589}], "attempt_jsons": [[[0, 0, 0, 0, 0], [0, 0, 0, 0, 0], [0, 0, 1, 0, 1], [0, 0, 5, 0, 5], [5, 5, 5, 5, 5]], [[1, 1, 1, 1, 1], [1, 1, 1, 1, 1], [1, 1, 1, 1, 1], [1, 1, 5, 1, 5], [5, 5, 5, 5, 5]], [[1, 1, 1, 1, 1], [1, 1, 1, 1, 1], [1, 1, 0, 1, 0], [1, 1, 5, 1, 5], [5, 5, 5, 5, 5]]], "max_idle_time": 10, "num_attempts": 3, "success": false, "time": 76.823, "timestamp": 1611800629.231, "uid": "47f2d0aa-1cae-4d22-93db-5d138d62315b"}, "bKSeoSpUGcUEiv3OcKDm": {"action_sequence": [{"action": {"tool": "copyFromInput"}, "grid": [[0, 0, 0, 0, 0], [0, 0, 0, 0, 0], [0, 0, 1, 0, 1], [0, 0, 5, 0, 5], [5, 5, 5, 5, 5]], "time": 29.121}, {"action": {"symbol": "2", "tool": "edit", "x": "4", "y": "4"}, "grid": [[0, 0, 0, 0, 0], [0, 0, 0, 0, 0], [0, 0, 1, 0, 1], [0, 0, 5, 0, 5], [5, 5, 5, 5, 2]], "time": 34.352}, {"action": {"symbol": "2", "tool": "edit", "x": "4", "y": "3"}, "grid": [[0, 0, 0, 0, 0], [0, 0, 0, 0, 0], [0, 0, 1, 0, 1], [0, 0, 5, 0, 5], [5, 5, 5, 2, 2]], "time": 35.211}, {"action": {"symbol": "2", "tool": "edit", "x": "4", "y": "3"}, "grid": [[0, 0, 0, 0, 0], [0, 0, 0, 0, 0], [0, 0, 1, 0, 1], [0, 0, 5, 0, 5], [5, 5, 5, 2, 2]], "time": 36.061}, {"action": {"symbol": "2", "tool": "edit", "x": "4", "y": "2"}, "grid": [[0, 0, 0, 0, 0], [0, 0, 0, 0, 0], [0, 0, 1, 0, 1], [0, 0, 5, 0, 5], [5, 5, 2, 2, 2]], "time": 36.773}, {"action": {"symbol": "2", "tool": "edit", "x": "4", "y": "1"}, "grid": [[0, 0, 0, 0, 0], [0, 0, 0, 0, 0], [0, 0, 1, 0, 1], [0, 0, 5, 0, 5], [5, 2, 2, 2, 2]], "time": 37.71}, {"action": {"symbol": "2", "tool": "edit", "x": "4", "y": "0"}, "grid": [[0, 0, 0, 0, 0], [0, 0, 0, 0, 0], [0, 0, 1, 0, 1], [0, 0, 5, 0, 5], [2, 2, 2, 2, 2]], "time": 38.54}, {"action": {"symbol": "2", "tool": "edit", "x": "3", "y": "2"}, "grid": [[0, 0, 0, 0, 0], [0, 0, 0, 0, 0], [0, 0, 1, 0, 1], [0, 0, 2, 0, 5], [2, 2, 2, 2, 2]], "time": 40.24}, {"action": {"symbol": "2", "tool": "edit", "x": "3", "y": "4"}, "grid": [[0, 0, 0, 0, 0], [0, 0, 0, 0, 0], [0, 0, 1, 0, 1], [0, 0, 2, 0, 2], [2, 2, 2, 2, 2]], "time": 41.444}, {"action": {"symbol": "5", "tool": "edit", "x": "2", "y": "2"}, "grid": [[0, 0, 0, 0, 0], [0, 0, 0, 0, 0], [0, 0, 5, 0, 1], [0, 0, 2, 0, 2], [2, 2, 2, 2, 2]], "time": 53.769}, {"action": {"symbol": "5", "tool": "edit", "x": "2", "y": "4"}, "grid": [[0, 0, 0, 0, 0], [0, 0, 0, 0, 0], [0, 0, 5, 0, 5], [0, 0, 2, 0, 2], [2, 2, 2, 2, 2]], "time": 54.813}, {"action": {"correct": false, "tool": "check"}, "grid": [[0, 0, 0, 0, 0], [0, 0, 0, 0, 0], [0, 0, 5, 0, 5], [0, 0, 2, 0, 2], [2, 2, 2, 2, 2]], "time": 56.362}, {"action": {"tool": "copyFromInput"}, "grid": [[0, 0, 0, 0, 0], [0, 0, 0, 0, 0], [0, 0, 1, 0, 1], [0, 0, 5, 0, 5], [5, 5, 5, 5, 5]], "time": 96.234}, {"action": {"symbol": "1", "tool": "edit", "x": "1", "y": "2"}, "grid": [[0, 0, 0, 0, 0], [0, 0, 1, 0, 0], [0, 0, 1, 0, 1], [0, 0, 5, 0, 5], [5, 5, 5, 5, 5]], "time": 99.202}, {"action": {"symbol": "1", "tool": "edit", "x": "1", "y": "4"}, "grid": [[0, 0, 0, 0, 0], [0, 0, 1, 0, 1], [0, 0, 1, 0, 1], [0, 0, 5, 0, 5], [5, 5, 5, 5, 5]], "time": 100.122}, {"action": {"correct": false, "tool": "check"}, "grid": [[0, 0, 0, 0, 0], [0, 0, 1, 0, 1], [0, 0, 1, 0, 1], [0, 0, 5, 0, 5], [5, 5, 5, 5, 5]], "time": 102.798}, {"action": {"symbol": "1", "tool": "edit", "x": "0", "y": "2"}, "grid": [[0, 0, 1, 0, 0], [0, 0, 1, 0, 1], [0, 0, 1, 0, 1], [0, 0, 5, 0, 5], [5, 5, 5, 5, 5]], "time": 105.332}, {"action": {"symbol": "1", "tool": "edit", "x": "0", "y": "2"}, "grid": [[0, 0, 1, 0, 0], [0, 0, 1, 0, 1], [0, 0, 1, 0, 1], [0, 0, 5, 0, 5], [5, 5, 5, 5, 5]], "time": 105.548}, {"action": {"symbol": "1", "tool": "edit", "x": "0", "y": "4"}, "grid": [[0, 0, 1, 0, 1], [0, 0, 1, 0, 1], [0, 0, 1, 0, 1], [0, 0, 5, 0, 5], [5, 5, 5, 5, 5]], "time": 106.427}, {"action": {"correct": false, "tool": "check"}, "grid": [[0, 0, 1, 0, 1], [0, 0, 1, 0, 1], [0, 0, 1, 0, 1], [0, 0, 5, 0, 5], [5, 5, 5, 5, 5]], "time": 108.584}], "attempt_jsons": [[[0, 0, 0, 0, 0], [0, 0, 0, 0, 0], [0, 0, 5, 0, 5], [0, 0, 2, 0, 2], [2, 2, 2, 2, 2]], [[0, 0, 0, 0, 0], [0, 0, 1, 0, 1], [0, 0, 1, 0, 1], [0, 0, 5, 0, 5], [5, 5, 5, 5, 5]], [[0, 0, 1, 0, 1], [0, 0, 1, 0, 1], [0, 0, 1, 0, 1], [0, 0, 5, 0, 5], [5, 5, 5, 5, 5]]], "max_idle_time": 15, "num_attempts": 3, "success": false, "time": 155.543, "timestamp": 1611903603.879, "uid": "139159cc-6d13-4140-b7e0-a625f4f283f5"}}, "confidence": 9, "description_time": 79, "do_description": "To make the output, you have to...In the input, you should see...specific the color change in two colors", "grid_description": "The output grid size...In the input, you should see...measure the color change in two colors", "max_idle_time": 5, "num_verification_attempts": 1, "see_description": "In the input, you should see...measure the color change in two colors", "succeeded_verification": true, "timestamp": 1611800526.831, "uid": "7418013b-6c86-4d4f-ac41-e418ac4f5e76", "verification_time": 40}, "aba0b648-1951-4da1-ae7f-62e33e34259e": {"action_sequence": [{"action": {"tool": "copyFromInput"}, "grid": [[0, 0, 0, 0, 0], [0, 0, 0, 0, 0], [0, 0, 1, 0, 1], [0, 0, 5, 0, 5], [5, 5, 5, 5, 5]], "time": 10.488}, {"action": {"symbol": "1", "tool": "edit", "x": "4", "y": "2"}, "grid": [[0, 0, 0, 0, 0], [0, 0, 0, 0, 0], [0, 0, 1, 0, 1], [0, 0, 5, 0, 5], [5, 5, 1, 5, 5]], "time": 16.638}, {"action": {"symbol": "1", "tool": "edit", "x": "4", "y": "4"}, "grid": [[0, 0, 0, 0, 0], [0, 0, 0, 0, 0], [0, 0, 1, 0, 1], [0, 0, 5, 0, 5], [5, 5, 1, 5, 1]], "time": 17.45}, {"action": {"symbol": "0", "tool": "edit", "x": "2", "y": "2"}, "grid": [[0, 0, 0, 0, 0], [0, 0, 0, 0, 0], [0, 0, 0, 0, 1], [0, 0, 5, 0, 5], [5, 5, 1, 5, 1]], "time": 19.241}, {"action": {"symbol": "0", "tool": "edit", "x": "2", "y": "4"}, "grid": [[0, 0, 0, 0, 0], [0, 0, 0, 0, 0], [0, 0, 0, 0, 0], [0, 0, 5, 0, 5], [5, 5, 1, 5, 1]], "time": 19.828}, {"action": {"correct": true, "tool": "check"}, "grid": [[0, 0, 0, 0, 0], [0, 0, 0, 0, 0], [0, 0, 0, 0, 0], [0, 0, 5, 0, 5], [5, 5, 1, 5, 1]], "time": 22.345}], "attempt_jsons": [[[0, 0, 0, 0, 0], [0, 0, 0, 0, 0], [0, 0, 0, 0, 0], [0, 0, 5, 0, 5], [5, 5, 1, 5, 1]]], "builds": {"2SnQSEvvWZzOgukABALh": {"action_sequence": [{"action": {"tool": "copyFromInput"}, "grid": [[0, 0, 0, 0, 0], [0, 0, 0, 0, 0], [0, 0, 1, 0, 1], [0, 0, 5, 0, 5], [5, 5, 5, 5, 5]], "time": 48.023}, {"action": {"symbol": "4", "tool": "edit", "x": "0", "y": "0"}, "grid": [[4, 0, 0, 0, 0], [0, 0, 0, 0, 0], [0, 0, 1, 0, 1], [0, 0, 5, 0, 5], [5, 5, 5, 5, 5]], "time": 52.327}, {"action": {"symbol": "4", "tool": "edit", "x": "0", "y": "1"}, "grid": [[4, 4, 0, 0, 0], [0, 0, 0, 0, 0], [0, 0, 1, 0, 1], [0, 0, 5, 0, 5], [5, 5, 5, 5, 5]], "time": 52.877}, {"action": {"symbol": "4", "tool": "edit", "x": "1", "y": "2"}, "grid": [[4, 4, 0, 0, 0], [0, 0, 4, 0, 0], [0, 0, 1, 0, 1], [0, 0, 5, 0, 5], [5, 5, 5, 5, 5]], "time": 53.702}, {"action": {"symbol": "4", "tool": "edit", "x": "2", "y": "0"}, "grid": [[4, 4, 0, 0, 0], [0, 0, 4, 0, 0], [4, 0, 1, 0, 1], [0, 0, 5, 0, 5], [5, 5, 5, 5, 5]], "time": 54.253}, {"action": {"symbol": "4", "tool": "edit", "x": "3", "y": "1"}, "grid": [[4, 4, 0, 0, 0], [0, 0, 4, 0, 0], [4, 0, 1, 0, 1], [0, 4, 5, 0, 5], [5, 5, 5, 5, 5]], "time": 55.222}, {"action": {"symbol": "0", "tool": "edit", "x": "2", "y": "2"}, "grid": [[4, 4, 0, 0, 0], [0, 0, 4, 0, 0], [4, 0, 0, 0, 1], [0, 4, 5, 0, 5], [5, 5, 5, 5, 5]], "time": 69.766}, {"action": {"symbol": "0", "tool": "edit", "x": "2", "y": "4"}, "grid": [[4, 4, 0, 0, 0], [0, 0, 4, 0, 0], [4, 0, 0, 0, 0], [0, 4, 5, 0, 5], [5, 5, 5, 5, 5]], "time": 70.364}, {"action": {"symbol": "0", "tool": "edit", "x": "1", "y": "2"}, "grid": [[4, 4, 0, 0, 0], [0, 0, 0, 0, 0], [4, 0, 0, 0, 0], [0, 4, 5, 0, 5], [5, 5, 5, 5, 5]], "time": 71.083}, {"action": {"symbol": "0", "tool": "edit", "x": "0", "y": "1"}, "grid": [[4, 0, 0, 0, 0], [0, 0, 0, 0, 0], [4, 0, 0, 0, 0], [0, 4, 5, 0, 5], [5, 5, 5, 5, 5]], "time": 72.074}, {"action": {"symbol": "0", "tool": "edit", "x": "0", "y": "1"}, "grid": [[4, 0, 0, 0, 0], [0, 0, 0, 0, 0], [4, 0, 0, 0, 0], [0, 4, 5, 0, 5], [5, 5, 5, 5, 5]], "time": 72.685}, {"action": {"symbol": "0", "tool": "edit", "x": "0", "y": "0"}, "grid": [[0, 0, 0, 0, 0], [0, 0, 0, 0, 0], [4, 0, 0, 0, 0], [0, 4, 5, 0, 5], [5, 5, 5, 5, 5]], "time": 73.57}, {"action": {"symbol": "0", "tool": "edit", "x": "2", "y": "0"}, "grid": [[0, 0, 0, 0, 0], [0, 0, 0, 0, 0], [0, 0, 0, 0, 0], [0, 4, 5, 0, 5], [5, 5, 5, 5, 5]], "time": 74.276}, {"action": {"symbol": "0", "tool": "edit", "x": "3", "y": "1"}, "grid": [[0, 0, 0, 0, 0], [0, 0, 0, 0, 0], [0, 0, 0, 0, 0], [0, 0, 5, 0, 5], [5, 5, 5, 5, 5]], "time": 74.913}, {"action": {"correct": false, "tool": "check"}, "grid": [[0, 0, 0, 0, 0], [0, 0, 0, 0, 0], [0, 0, 0, 0, 0], [0, 0, 5, 0, 5], [5, 5, 5, 5, 5]], "time": 76.818}, {"action": {"symbol": "0", "tool": "edit", "x": "3", "y": "2"}, "grid": [[0, 0, 0, 0, 0], [0, 0, 0, 0, 0], [0, 0, 0, 0, 0], [0, 0, 0, 0, 5], [5, 5, 5, 5, 5]], "time": 78.699}, {"action": {"symbol": "0", "tool": "edit", "x": "3", "y": "4"}, "grid": [[0, 0, 0, 0, 0], [0, 0, 0, 0, 0], [0, 0, 0, 0, 0], [0, 0, 0, 0, 0], [5, 5, 5, 5, 5]], "time": 79.262}, {"action": {"symbol": "0", "tool": "edit", "x": "4", "y": "4"}, "grid": [[0, 0, 0, 0, 0], [0, 0, 0, 0, 0], [0, 0, 0, 0, 0], [0, 0, 0, 0, 0], [5, 5, 5, 5, 0]], "time": 80.004}, {"action": {"symbol": "0", "tool": "edit", "x": "4", "y": "3"}, "grid": [[0, 0, 0, 0, 0], [0, 0, 0, 0, 0], [0, 0, 0, 0, 0], [0, 0, 0, 0, 0], [5, 5, 5, 0, 0]], "time": 81.451}, {"action": {"symbol": "0", "tool": "edit", "x": "4", "y": "1"}, "grid": [[0, 0, 0, 0, 0], [0, 0, 0, 0, 0], [0, 0, 0, 0, 0], [0, 0, 0, 0, 0], [5, 0, 5, 0, 0]], "time": 82.634}, {"action": {"symbol": "0", "tool": "edit", "x": "4", "y": "0"}, "grid": [[0, 0, 0, 0, 0], [0, 0, 0, 0, 0], [0, 0, 0, 0, 0], [0, 0, 0, 0, 0], [0, 0, 5, 0, 0]], "time": 83.221}, {"action": {"symbol": "0", "tool": "edit", "x": "4", "y": "2"}, "grid": [[0, 0, 0, 0, 0], [0, 0, 0, 0, 0], [0, 0, 0, 0, 0], [0, 0, 0, 0, 0], [0, 0, 0, 0, 0]], "time": 84.142}, {"action": {"correct": false, "tool": "check"}, "grid": [[0, 0, 0, 0, 0], [0, 0, 0, 0, 0], [0, 0, 0, 0, 0], [0, 0, 0, 0, 0], [0, 0, 0, 0, 0]], "time": 105.115}, {"action": {"symbol": "0", "tool": "edit", "x": "2", "y": "2"}, "grid": [[0, 0, 0, 0, 0], [0, 0, 0, 0, 0], [0, 0, 0, 0, 0], [0, 0, 0, 0, 0], [0, 0, 0, 0, 0]], "time": 106.474}, {"action": {"symbol": "0", "tool": "edit", "x": "2", "y": "1"}, "grid": [[0, 0, 0, 0, 0], [0, 0, 0, 0, 0], [0, 0, 0, 0, 0], [0, 0, 0, 0, 0], [0, 0, 0, 0, 0]], "time": 107.144}, {"action": {"symbol": "2", "tool": "edit", "x": "3", "y": "2"}, "grid": [[0, 0, 0, 0, 0], [0, 0, 0, 0, 0], [0, 0, 0, 0, 0], [0, 0, 2, 0, 0], [0, 0, 0, 0, 0]], "time": 109.727}, {"action": {"symbol": "2", "tool": "edit", "x": "1", "y": "1"}, "grid": [[0, 0, 0, 0, 0], [0, 2, 0, 0, 0], [0, 0, 0, 0, 0], [0, 0, 2, 0, 0], [0, 0, 0, 0, 0]], "time": 110.242}, {"action": {"symbol": "2", "tool": "edit", "x": "1", "y": "2"}, "grid": [[0, 0, 0, 0, 0], [0, 2, 2, 0, 0], [0, 0, 0, 0, 0], [0, 0, 2, 0, 0], [0, 0, 0, 0, 0]], "time": 110.748}, {"action": {"correct": false, "tool": "check"}, "grid": [[0, 0, 0, 0, 0], [0, 2, 2, 0, 0], [0, 0, 0, 0, 0], [0, 0, 2, 0, 0], [0, 0, 0, 0, 0]], "time": 112.066}], "attempt_jsons": [[[0, 0, 0, 0, 0], [0, 0, 0, 0, 0], [0, 0, 0, 0, 0], [0, 0, 5, 0, 5], [5, 5, 5, 5, 5]], [[0, 0, 0, 0, 0], [0, 0, 0, 0, 0], [0, 0, 0, 0, 0], [0, 0, 0, 0, 0], [0, 0, 0, 0, 0]], [[0, 0, 0, 0, 0], [0, 2, 2, 0, 0], [0, 0, 0, 0, 0], [0, 0, 2, 0, 0], [0, 0, 0, 0, 0]]], "max_idle_time": 40, "num_attempts": 3, "success": false, "time": 134.956, "timestamp": 1617166573.613, "uid": "d8474ec1-cb18-4967-9897-f57a6af99c92"}, "o2XnXRcBFVLTyaOkhykV": {"action_sequence": [{"action": {"tool": "copyFromInput"}, "grid": [[0, 0, 0, 0, 0], [0, 0, 0, 0, 0], [0, 0, 1, 0, 1], [0, 0, 5, 0, 5], [5, 5, 5, 5, 5]], "time": 16.669}, {"action": {"symbol": "1", "tool": "edit", "x": "4", "y": "2"}, "grid": [[0, 0, 0, 0, 0], [0, 0, 0, 0, 0], [0, 0, 1, 0, 1], [0, 0, 5, 0, 5], [5, 5, 1, 5, 5]], "time": 18.258}, {"action": {"symbol": "1", "tool": "edit", "x": "4", "y": "4"}, "grid": [[0, 0, 0, 0, 0], [0, 0, 0, 0, 0], [0, 0, 1, 0, 1], [0, 0, 5, 0, 5], [5, 5, 1, 5, 1]], "time": 18.525}, {"action": {"correct": false, "tool": "check"}, "grid": [[0, 0, 0, 0, 0], [0, 0, 0, 0, 0], [0, 0, 1, 0, 1], [0, 0, 5, 0, 5], [5, 5, 1, 5, 1]], "time": 19.24}, {"action": {"symbol": "0", "tool": "edit", "x": "4", "y": "0"}, "grid": [[0, 0, 0, 0, 0], [0, 0, 0, 0, 0], [0, 0, 1, 0, 1], [0, 0, 5, 0, 5], [0, 5, 1, 5, 1]], "time": 22.952}, {"action": {"symbol": "0", "tool": "edit", "x": "4", "y": "1"}, "grid": [[0, 0, 0, 0, 0], [0, 0, 0, 0, 0], [0, 0, 1, 0, 1], [0, 0, 5, 0, 5], [0, 0, 1, 5, 1]], "time": 23.169}, {"action": {"symbol": "0", "tool": "edit", "x": "3", "y": "2"}, "grid": [[0, 0, 0, 0, 0], [0, 0, 0, 0, 0], [0, 0, 1, 0, 1], [0, 0, 0, 0, 5], [0, 0, 1, 5, 1]], "time": 23.441}, {"action": {"symbol": "0", "tool": "edit", "x": "4", "y": "3"}, "grid": [[0, 0, 0, 0, 0], [0, 0, 0, 0, 0], [0, 0, 1, 0, 1], [0, 0, 0, 0, 5], [0, 0, 1, 0, 1]], "time": 23.796}, {"action": {"symbol": "0", "tool": "edit", "x": "3", "y": "4"}, "grid": [[0, 0, 0, 0, 0], [0, 0, 0, 0, 0], [0, 0, 1, 0, 1], [0, 0, 0, 0, 0], [0, 0, 1, 0, 1]], "time": 24.078}, {"action": {"correct": false, "tool": "check"}, "grid": [[0, 0, 0, 0, 0], [0, 0, 0, 0, 0], [0, 0, 1, 0, 1], [0, 0, 0, 0, 0], [0, 0, 1, 0, 1]], "time": 28.099}, {"action": {"tool": "copyFromInput"}, "grid": [[0, 0, 0, 0, 0], [0, 0, 0, 0, 0], [0, 0, 1, 0, 1], [0, 0, 5, 0, 5], [5, 5, 5, 5, 5]], "time": 33.819}, {"action": {"symbol": "1", "tool": "edit", "x": "3", "y": "2"}, "grid": [[0, 0, 0, 0, 0], [0, 0, 0, 0, 0], [0, 0, 1, 0, 1], [0, 0, 1, 0, 5], [5, 5, 5, 5, 5]], "time": 35.569}, {"action": {"symbol": "1", "tool": "edit", "x": "4", "y": "2"}, "grid": [[0, 0, 0, 0, 0], [0, 0, 0, 0, 0], [0, 0, 1, 0, 1], [0, 0, 1, 0, 5], [5, 5, 1, 5, 5]], "time": 35.773}, {"action": {"symbol": "1", "tool": "edit", "x": "3", "y": "4"}, "grid": [[0, 0, 0, 0, 0], [0, 0, 0, 0, 0], [0, 0, 1, 0, 1], [0, 0, 1, 0, 1], [5, 5, 1, 5, 5]], "time": 36.186}, {"action": {"symbol": "1", "tool": "edit", "x": "4", "y": "4"}, "grid": [[0, 0, 0, 0, 0], [0, 0, 0, 0, 0], [0, 0, 1, 0, 1], [0, 0, 1, 0, 1], [5, 5, 1, 5, 1]], "time": 36.427}, {"action": {"tool": "copyFromInput"}, "grid": [[0, 0, 0, 0, 0], [0, 0, 0, 0, 0], [0, 0, 1, 0, 1], [0, 0, 5, 0, 5], [5, 5, 5, 5, 5]], "time": 42.359}, {"action": {"symbol": "1", "tool": "edit", "x": "4", "y": "2"}, "grid": [[0, 0, 0, 0, 0], [0, 0, 0, 0, 0], [0, 0, 1, 0, 1], [0, 0, 5, 0, 5], [5, 5, 1, 5, 5]], "time": 44.053}, {"action": {"symbol": "1", "tool": "edit", "x": "4", "y": "4"}, "grid": [[0, 0, 0, 0, 0], [0, 0, 0, 0, 0], [0, 0, 1, 0, 1], [0, 0, 5, 0, 5], [5, 5, 1, 5, 1]], "time": 44.362}, {"action": {"symbol": "5", "tool": "edit", "x": "2", "y": "2"}, "grid": [[0, 0, 0, 0, 0], [0, 0, 0, 0, 0], [0, 0, 5, 0, 1], [0, 0, 5, 0, 5], [5, 5, 1, 5, 1]], "time": 46.033}, {"action": {"symbol": "5", "tool": "edit", "x": "2", "y": "4"}, "grid": [[0, 0, 0, 0, 0], [0, 0, 0, 0, 0], [0, 0, 5, 0, 5], [0, 0, 5, 0, 5], [5, 5, 1, 5, 1]], "time": 46.38}, {"action": {"correct": false, "tool": "check"}, "grid": [[0, 0, 0, 0, 0], [0, 0, 0, 0, 0], [0, 0, 5, 0, 5], [0, 0, 5, 0, 5], [5, 5, 1, 5, 1]], "time": 47.368}], "attempt_jsons": [[[0, 0, 0, 0, 0], [0, 0, 0, 0, 0], [0, 0, 1, 0, 1], [0, 0, 5, 0, 5], [5, 5, 1, 5, 1]], [[0, 0, 0, 0, 0], [0, 0, 0, 0, 0], [0, 0, 1, 0, 1], [0, 0, 0, 0, 0], [0, 0, 1, 0, 1]], [[0, 0, 0, 0, 0], [0, 0, 0, 0, 0], [0, 0, 5, 0, 5], [0, 0, 5, 0, 5], [5, 5, 1, 5, 1]]], "max_idle_time": 5, "num_attempts": 3, "success": false, "time": 74.669, "timestamp": 1611781129.017, "uid": "c473c306-cd07-43fb-a725-9c1981855db5"}}, "confidence": 5, "description_time": 279, "do_description": "To make the output, you have to...take the blue dots and place them two squares down.with the background still fully black", "grid_description": "The output grid size...is the same", "max_idle_time": 110, "num_verification_attempts": 1, "see_description": "In the input, you should see...gray grid with blue dots on top", "succeeded_verification": true, "timestamp": 1611781021.757, "uid": "925aa3bb-a02b-4de8-bfe1-2301ec59fdd7", "verification_time": 25}, "cd083108-f890-41fd-8fcc-e70f459eca0a": {"action_sequence": [{"action": {"tool": "copyFromInput"}, "grid": [[0, 0, 0, 0, 0], [0, 0, 0, 0, 0], [0, 0, 1, 0, 1], [0, 0, 5, 0, 5], [5, 5, 5, 5, 5]], "time": 181.161}, {"action": {"correct": false, "tool": "check"}, "grid": [[0, 0, 0, 0, 0], [0, 0, 0, 0, 0], [0, 0, 1, 0, 1], [0, 0, 5, 0, 5], [5, 5, 5, 5, 5]], "time": 190.782}, {"action": {"tool": "copyFromInput"}, "grid": [[0, 0, 0, 0, 0], [0, 0, 0, 0, 0], [0, 0, 1, 0, 1], [0, 0, 5, 0, 5], [5, 5, 5, 5, 5]], "time": 207.33}, {"action": {"symbol": "5", "tool": "edit", "x": "3", "y": "0"}, "grid": [[0, 0, 0, 0, 0], [0, 0, 0, 0, 0], [0, 0, 1, 0, 1], [5, 0, 5, 0, 5], [5, 5, 5, 5, 5]], "time": 234.245}, {"action": {"symbol": "1", "tool": "edit", "x": "2", "y": "0"}, "grid": [[0, 0, 0, 0, 0], [0, 0, 0, 0, 0], [1, 0, 1, 0, 1], [5, 0, 5, 0, 5], [5, 5, 5, 5, 5]], "time": 236.731}, {"action": {"correct": false, "tool": "check"}, "grid": [[0, 0, 0, 0, 0], [0, 0, 0, 0, 0], [1, 0, 1, 0, 1], [5, 0, 5, 0, 5], [5, 5, 5, 5, 5]], "time": 238.145}, {"action": {"tool": "copyFromInput"}, "grid": [[0, 0, 0, 0, 0], [0, 0, 0, 0, 0], [0, 0, 1, 0, 1], [0, 0, 5, 0, 5], [5, 5, 5, 5, 5]], "time": 250.053}, {"action": {"symbol": "1", "tool": "edit", "x": "2", "y": "1"}, "grid": [[0, 0, 0, 0, 0], [0, 0, 0, 0, 0], [0, 1, 1, 0, 1], [0, 0, 5, 0, 5], [5, 5, 5, 5, 5]], "time": 255.245}, {"action": {"symbol": "1", "tool": "edit", "x": "2", "y": "3"}, "grid": [[0, 0, 0, 0, 0], [0, 0, 0, 0, 0], [0, 1, 1, 1, 1], [0, 0, 5, 0, 5], [5, 5, 5, 5, 5]], "time": 255.85}, {"action": {"symbol": "0", "tool": "edit", "x": "3", "y": "2"}, "grid": [[0, 0, 0, 0, 0], [0, 0, 0, 0, 0], [0, 1, 1, 1, 1], [0, 0, 0, 0, 5], [5, 5, 5, 5, 5]], "time": 259.53}, {"action": {"symbol": "0", "tool": "edit", "x": "3", "y": "4"}, "grid": [[0, 0, 0, 0, 0], [0, 0, 0, 0, 0], [0, 1, 1, 1, 1], [0, 0, 0, 0, 0], [5, 5, 5, 5, 5]], "time": 261.027}, {"action": {"symbol": "0", "tool": "edit", "x": "2", "y": "4"}, "grid": [[0, 0, 0, 0, 0], [0, 0, 0, 0, 0], [0, 1, 1, 1, 0], [0, 0, 0, 0, 0], [5, 5, 5, 5, 5]], "time": 262.16}, {"action": {"symbol": "0", "tool": "edit", "x": "2", "y": "2"}, "grid": [[0, 0, 0, 0, 0], [0, 0, 0, 0, 0], [0, 1, 0, 1, 0], [0, 0, 0, 0, 0], [5, 5, 5, 5, 5]], "time": 262.748}, {"action": {"symbol": "5", "tool": "edit", "x": "3", "y": "3"}, "grid": [[0, 0, 0, 0, 0], [0, 0, 0, 0, 0], [0, 1, 0, 1, 0], [0, 0, 0, 5, 0], [5, 5, 5, 5, 5]], "time": 264.943}, {"action": {"symbol": "5", "tool": "edit", "x": "3", "y": "1"}, "grid": [[0, 0, 0, 0, 0], [0, 0, 0, 0, 0], [0, 1, 0, 1, 0], [0, 5, 0, 5, 0], [5, 5, 5, 5, 5]], "time": 265.402}, {"action": {"correct": false, "tool": "check"}, "grid": [[0, 0, 0, 0, 0], [0, 0, 0, 0, 0], [0, 1, 0, 1, 0], [0, 5, 0, 5, 0], [5, 5, 5, 5, 5]], "time": 267.531}], "attempt_jsons": [[[0, 0, 0, 0, 0], [0, 0, 0, 0, 0], [0, 0, 1, 0, 1], [0, 0, 5, 0, 5], [5, 5, 5, 5, 5]], [[0, 0, 0, 0, 0], [0, 0, 0, 0, 0], [1, 0, 1, 0, 1], [5, 0, 5, 0, 5], [5, 5, 5, 5, 5]], [[0, 0, 0, 0, 0], [0, 0, 0, 0, 0], [0, 1, 0, 1, 0], [0, 5, 0, 5, 0], [5, 5, 5, 5, 5]]], "builds": {}, "confidence": null, "description_time": 1121, "do_description": "To make the output, you have to...start with gray as the bottom line across, then no more than 2 more on top of that line, with blue being the top square of each line, with a black inbetween each line, making a \"U\" shape.", "grid_description": "The output grid size...is the same", "max_idle_time": 480, "num_verification_attempts": 3, "see_description": "In the input, you should see...gray grid with blue dots on top", "succeeded_verification": false, "timestamp": 1611801817.857, "uid": "1d1046d6-7c15-4561-acea-5ebd6b810c98", "verification_time": 267}, "eaba1f4b-ccbc-4873-b6e9-81c2ae428c68": {"action_sequence": [{"action": {"tool": "copyFromInput"}, "grid": [[0, 0, 0, 0, 0], [0, 0, 0, 0, 0], [0, 0, 1, 0, 1], [0, 0, 5, 0, 5], [5, 5, 5, 5, 5]], "time": 33.303}, {"action": {"symbol": "1", "tool": "floodfill", "x": "4", "y": "2"}, "grid": [[0, 0, 0, 0, 0], [0, 0, 0, 0, 0], [0, 0, 1, 0, 1], [0, 0, 1, 0, 1], [1, 1, 1, 1, 1]], "time": 44.505}, {"action": {"symbol": "1", "tool": "floodfill", "x": "4", "y": "2"}, "grid": [[0, 0, 0, 0, 0], [0, 0, 0, 0, 0], [0, 0, 1, 0, 1], [0, 0, 1, 0, 1], [1, 1, 1, 1, 1]], "time": 46.533}, {"action": {"symbol": "0", "tool": "floodfill", "x": "4", "y": "2"}, "grid": [[0, 0, 0, 0, 0], [0, 0, 0, 0, 0], [0, 0, 0, 0, 0], [0, 0, 0, 0, 0], [0, 0, 0, 0, 0]], "time": 50.597}, {"action": {"tool": "copyFromInput"}, "grid": [[0, 0, 0, 0, 0], [0, 0, 0, 0, 0], [0, 0, 1, 0, 1], [0, 0, 5, 0, 5], [5, 5, 5, 5, 5]], "time": 54.423}, {"action": {"symbol": "1", "tool": "floodfill", "x": "4", "y": "2"}, "grid": [[0, 0, 0, 0, 0], [0, 0, 0, 0, 0], [0, 0, 1, 0, 1], [0, 0, 1, 0, 1], [1, 1, 1, 1, 1]], "time": 62.285}, {"action": {"tool": "copyFromInput"}, "grid": [[0, 0, 0, 0, 0], [0, 0, 0, 0, 0], [0, 0, 1, 0, 1], [0, 0, 5, 0, 5], [5, 5, 5, 5, 5]], "time": 67.861}, {"action": {"symbol": "1", "tool": "edit", "x": "4", "y": "2"}, "grid": [[0, 0, 0, 0, 0], [0, 0, 0, 0, 0], [0, 0, 1, 0, 1], [0, 0, 5, 0, 5], [5, 5, 1, 5, 5]], "time": 99.444}, {"action": {"symbol": "1", "tool": "edit", "x": "4", "y": "4"}, "grid": [[0, 0, 0, 0, 0], [0, 0, 0, 0, 0], [0, 0, 1, 0, 1], [0, 0, 5, 0, 5], [5, 5, 1, 5, 1]], "time": 100.364}, {"action": {"symbol": "0", "tool": "edit", "x": "2", "y": "2"}, "grid": [[0, 0, 0, 0, 0], [0, 0, 0, 0, 0], [0, 0, 0, 0, 1], [0, 0, 5, 0, 5], [5, 5, 1, 5, 1]], "time": 102.516}, {"action": {"symbol": "0", "tool": "edit", "x": "2", "y": "4"}, "grid": [[0, 0, 0, 0, 0], [0, 0, 0, 0, 0], [0, 0, 0, 0, 0], [0, 0, 5, 0, 5], [5, 5, 1, 5, 1]], "time": 103.22}, {"action": {"correct": true, "tool": "check"}, "grid": [[0, 0, 0, 0, 0], [0, 0, 0, 0, 0], [0, 0, 0, 0, 0], [0, 0, 5, 0, 5], [5, 5, 1, 5, 1]], "time": 105.356}], "attempt_jsons": [[[0, 0, 0, 0, 0], [0, 0, 0, 0, 0], [0, 0, 0, 0, 0], [0, 0, 5, 0, 5], [5, 5, 1, 5, 1]]], "builds": {"1B99pBTQvcqRok6L81Hi": {"action_sequence": [{"action": {"tool": "copyFromInput"}, "grid": [[0, 0, 0, 0, 0], [0, 0, 0, 0, 0], [0, 0, 1, 0, 1], [0, 0, 5, 0, 5], [5, 5, 5, 5, 5]], "time": 18.507}, {"action": {"symbol": "1", "tool": "edit", "x": "2", "y": "2"}, "grid": [[0, 0, 0, 0, 0], [0, 0, 0, 0, 0], [0, 0, 1, 0, 0], [0, 0, 0, 0, 0], [0, 0, 0, 0, 0]], "time": 31.857}, {"action": {"symbol": "1", "tool": "edit", "x": "2", "y": "4"}, "grid": [[0, 0, 0, 0, 0], [0, 0, 0, 0, 0], [0, 0, 1, 0, 1], [0, 0, 0, 0, 0], [0, 0, 0, 0, 0]], "time": 32.544}, {"action": {"correct": false, "tool": "check"}, "grid": [[0, 0, 0, 0, 0], [0, 0, 0, 0, 0], [0, 0, 1, 0, 1], [0, 0, 0, 0, 0], [0, 0, 0, 0, 0]], "time": 34.926}, {"action": {"symbol": "5", "tool": "edit", "x": "4", "y": "0"}, "grid": [[0, 0, 0, 0, 0], [0, 0, 0, 0, 0], [0, 0, 0, 0, 0], [0, 0, 0, 0, 0], [5, 0, 0, 0, 0]], "time": 45.536}, {"action": {"symbol": "5", "tool": "edit", "x": "4", "y": "0"}, "grid": [[0, 0, 0, 0, 0], [0, 0, 0, 0, 0], [0, 0, 0, 0, 0], [0, 0, 0, 0, 0], [5, 0, 0, 0, 0]], "time": 45.553}, {"action": {"symbol": "5", "tool": "edit", "x": "4", "y": "1"}, "grid": [[0, 0, 0, 0, 0], [0, 0, 0, 0, 0], [0, 0, 0, 0, 0], [0, 0, 0, 0, 0], [5, 5, 0, 0, 0]], "time": 45.928}, {"action": {"symbol": "5", "tool": "edit", "x": "4", "y": "2"}, "grid": [[0, 0, 0, 0, 0], [0, 0, 0, 0, 0], [0, 0, 0, 0, 0], [0, 0, 0, 0, 0], [5, 5, 5, 0, 0]], "time": 46.464}, {"action": {"symbol": "5", "tool": "edit", "x": "3", "y": "2"}, "grid": [[0, 0, 0, 0, 0], [0, 0, 0, 0, 0], [0, 0, 0, 0, 0], [0, 0, 5, 0, 0], [5, 5, 5, 0, 0]], "time": 47.328}, {"action": {"symbol": "5", "tool": "edit", "x": "4", "y": "3"}, "grid": [[0, 0, 0, 0, 0], [0, 0, 0, 0, 0], [0, 0, 0, 0, 0], [0, 0, 5, 0, 0], [5, 5, 5, 5, 0]], "time": 48.104}, {"action": {"symbol": "5", "tool": "edit", "x": "4", "y": "4"}, "grid": [[0, 0, 0, 0, 0], [0, 0, 0, 0, 0], [0, 0, 0, 0, 0], [0, 0, 5, 0, 0], [5, 5, 5, 5, 5]], "time": 48.52}, {"action": {"symbol": "5", "tool": "edit", "x": "3", "y": "4"}, "grid": [[0, 0, 0, 0, 0], [0, 0, 0, 0, 0], [0, 0, 0, 0, 0], [0, 0, 5, 0, 5], [5, 5, 5, 5, 5]], "time": 48.888}, {"action": {"correct": false, "tool": "check"}, "grid": [[0, 0, 0, 0, 0], [0, 0, 0, 0, 0], [0, 0, 0, 0, 0], [0, 0, 5, 0, 5], [5, 5, 5, 5, 5]], "time": 51.117}, {"action": {"tool": "copyFromInput"}, "grid": [[0, 0, 0, 0, 0], [0, 0, 0, 0, 0], [0, 0, 1, 0, 1], [0, 0, 5, 0, 5], [5, 5, 5, 5, 5]], "time": 52.966}, {"action": {"symbol": "1", "tool": "edit", "x": "1", "y": "1"}, "grid": [[0, 0, 0, 0, 0], [0, 1, 0, 0, 0], [0, 0, 0, 0, 0], [0, 0, 0, 0, 0], [0, 0, 0, 0, 0]], "time": 59.625}, {"action": {"symbol": "1", "tool": "edit", "x": "1", "y": "3"}, "grid": [[0, 0, 0, 0, 0], [0, 1, 0, 1, 0], [0, 0, 0, 0, 0], [0, 0, 0, 0, 0], [0, 0, 0, 0, 0]], "time": 60.153}, {"action": {"correct": false, "tool": "check"}, "grid": [[0, 0, 0, 0, 0], [0, 1, 0, 1, 0], [0, 0, 0, 0, 0], [0, 0, 0, 0, 0], [0, 0, 0, 0, 0]], "time": 63.493}], "attempt_jsons": [[[0, 0, 0, 0, 0], [0, 0, 0, 0, 0], [0, 0, 1, 0, 1], [0, 0, 0, 0, 0], [0, 0, 0, 0, 0]], [[0, 0, 0, 0, 0], [0, 0, 0, 0, 0], [0, 0, 0, 0, 0], [0, 0, 5, 0, 5], [5, 5, 5, 5, 5]], [[0, 0, 0, 0, 0], [0, 1, 0, 1, 0], [0, 0, 0, 0, 0], [0, 0, 0, 0, 0], [0, 0, 0, 0, 0]]], "max_idle_time": 10, "num_attempts": 3, "success": false, "time": 90.099, "timestamp": 1611925049.184, "uid": "cf93d62e-4004-4b09-935c-b8e7f572c0d9"}, "fUnD7ljmpHOaRIlRNaNH": {"action_sequence": [{"action": {"tool": "copyFromInput"}, "grid": [[0, 0, 0, 0, 0], [0, 0, 0, 0, 0], [0, 0, 1, 0, 1], [0, 0, 5, 0, 5], [5, 5, 5, 5, 5]], "time": 37.799}, {"action": {"symbol": "1", "tool": "edit", "x": "4", "y": "2"}, "grid": [[0, 0, 0, 0, 0], [0, 0, 0, 0, 0], [0, 0, 1, 0, 1], [0, 0, 5, 0, 5], [5, 5, 1, 5, 5]], "time": 45.851}, {"action": {"symbol": "1", "tool": "edit", "x": "4", "y": "4"}, "grid": [[0, 0, 0, 0, 0], [0, 0, 0, 0, 0], [0, 0, 1, 0, 1], [0, 0, 5, 0, 5], [5, 5, 1, 5, 1]], "time": 46.715}, {"action": {"symbol": "0", "tool": "edit", "x": "2", "y": "2"}, "grid": [[0, 0, 0, 0, 0], [0, 0, 0, 0, 0], [0, 0, 0, 0, 1], [0, 0, 5, 0, 5], [5, 5, 1, 5, 1]], "time": 53.947}, {"action": {"symbol": "0", "tool": "edit", "x": "2", "y": "4"}, "grid": [[0, 0, 0, 0, 0], [0, 0, 0, 0, 0], [0, 0, 0, 0, 0], [0, 0, 5, 0, 5], [5, 5, 1, 5, 1]], "time": 54.451}, {"action": {"correct": true, "tool": "check"}, "grid": [[0, 0, 0, 0, 0], [0, 0, 0, 0, 0], [0, 0, 0, 0, 0], [0, 0, 5, 0, 5], [5, 5, 1, 5, 1]], "time": 56.156}], "attempt_jsons": [[[0, 0, 0, 0, 0], [0, 0, 0, 0, 0], [0, 0, 0, 0, 0], [0, 0, 5, 0, 5], [5, 5, 1, 5, 1]]], "max_idle_time": 20, "num_attempts": 1, "success": true, "time": 56.159, "timestamp": 1617218777.631, "uid": "f6060de5-a71c-48e5-b1ec-84d294034d2e"}}, "confidence": 5, "description_time": 481, "do_description": "To make the output, you have to...change blue grids to black background, count two steps below each grid's initial placement and fill with blue", "grid_description": "The output grid size...the two blue grids have been moved two steps downwards", "max_idle_time": 35, "num_verification_attempts": 1, "see_description": "In the input, you should see... two blue colored grids on top of the grey grids, a black grid is between the two blue grids", "succeeded_verification": true, "timestamp": 1611921028.598, "uid": "64a4f70f-eb0a-461f-90ca-16bffc7a341f", "verification_time": 114}}, "name": "3618c87e.json", "test": [{"input": [[0, 0, 0, 0, 0], [0, 0, 0, 0, 0], [0, 0, 1, 0, 1], [0, 0, 5, 0, 5], [5, 5, 5, 5, 5]], "output": [[0, 0, 0, 0, 0], [0, 0, 0, 0, 0], [0, 0, 0, 0, 0], [0, 0, 5, 0, 5], [5, 5, 1, 5, 1]]}], "train": [{"input": [[0, 0, 0, 0, 0], [0, 0, 0, 0, 0], [0, 0, 1, 0, 0], [0, 0, 5, 0, 0], [5, 5, 5, 5, 5]], "output": [[0, 0, 0, 0, 0], [0, 0, 0, 0, 0], [0, 0, 0, 0, 0], [0, 0, 5, 0, 0], [5, 5, 1, 5, 5]]}, {"input": [[0, 0, 0, 0, 0], [0, 0, 0, 0, 0], [0, 1, 0, 1, 0], [0, 5, 0, 5, 0], [5, 5, 5, 5, 5]], "output": [[0, 0, 0, 0, 0], [0, 0, 0, 0, 0], [0, 0, 0, 0, 0], [0, 5, 0, 5, 0], [5, 1, 5, 1, 5]]}, {"input": [[0, 0, 0, 0, 0], [0, 0, 0, 0, 0], [0, 1, 0, 0, 1], [0, 5, 0, 0, 5], [5, 5, 5, 5, 5]], "output": [[0, 0, 0, 0, 0], [0, 0, 0, 0, 0], [0, 0, 0, 0, 0], [0, 5, 0, 0, 5], [5, 1, 5, 5, 1]]}]}